LICENSE
MANIFEST.in
README.md
setup.py
ndocker/__init__.py
ndocker/cmds.py
ndocker/command_line.py
ndocker/ne.py
ndocker/necfg.py
ndocker/networks.py
ndocker.egg-info/PKG-INFO
ndocker.egg-info/SOURCES.txt
ndocker.egg-info/dependency_links.txt
ndocker.egg-info/entry_points.txt
ndocker.egg-info/not-zip-safe
ndocker.egg-info/requires.txt
ndocker.egg-info/top_level.txt
ndocker/common/__init__.py
ndocker/common/click_ext.py
ndocker/common/logger.py
ndocker/common/parser.py
ndocker/common/utils.py
ndocker/common/yamler.py
ndocker/data/fzc.yaml
ndocker/data/fzm.yaml
ndocker/data/host.yaml
ndocker/docker/__init__.py
ndocker/docker/docker_cmd.py
ndocker/ovs/__init__.py
ndocker/ovs/vsctl.py