Metadata-Version: 1.1
Name: ndocker
Version: 1.0.5
Summary: docker network configration
Home-page: http://github.com/codlin/ndocker
Author: Sean Z
Author-email: sean.z.ealous@gmail.com
License: UNKNOWN
Platform: UNKNOWN
Classifier: Development Status :: 3 - Alpha
Classifier: Intended Audience :: Developers
Classifier: Topic :: Software Development :: Libraries :: Python Modules
Classifier: License :: OSI Approved :: Apache Software License
Classifier: Programming Language :: Python :: 2.7
